pytest_performance.py
pytest_performance-0.1.0.dist-info/LICENSE
pytest_performance-0.1.0.dist-info/METADATA
pytest_performance-0.1.0.dist-info/WHEEL
pytest_performance-0.1.0.dist-info/entry_points.txt
pytest_performance-0.1.0.dist-info/top_level.txt
pytest_performance-0.1.0.dist-info/RECORD
