Metadata-Version: 2.1
Name: pytest-performance
Version: 0.1.0
Summary: A simple plugin to ensure the execution of critical sections of code has not been impacted
Home-page: https://github.com/rupertcw/pytest-performance
Author: Rupert Cobbe-Warburton
Author-email: rupertcw10@gmail.com
Maintainer: Rupert Cobbe-Warburton
Maintainer-email: rupertcw10@gmail.com
License: MIT
Platform: UNKNOWN
Classifier: Development Status :: 5 - Production/Stable
Classifier: Framework :: Pytest
Classifier: Intended Audience :: Developers
Classifier: Topic :: Software Development :: Testing
Classifier: Programming Language :: Python
Classifier: Programming Language :: Python :: 3
Classifier: Programming Language :: Python :: 3.7
Classifier: Programming Language :: Python :: 3 :: Only
Classifier: Programming Language :: Python :: Implementation :: CPython
Classifier: Operating System :: OS Independent
Classifier: License :: OSI Approved :: MIT License
Requires-Python: >=3.7
Requires-Dist: pytest (>=3.7.0)
Requires-Dist: pint (<1.0,>=0.15)
Requires-Dist: numpy
